<?xml version="1.0"?>
<!DOCTYPE package SYSTEM "DTD/package.dtd">
<data>
	<import>
		<portalboxitem name="rgalleryleft">
			<className>RGalleryBox</className>
			<cacheBuilderClass></cacheBuilderClass>
			<boxType>2</boxType>
			<useCache>0</useCache>
			<sortOrder>4</sortOrder>
			<boxActivation>1</boxActivation>
		</portalboxitem>
		
		<portalboxitem name="rgallerycenter">
			<className>RGalleryBox</className>
			<cacheBuilderClass></cacheBuilderClass>
			<boxType>1</boxType>
			<useCache>0</useCache>
			<sortOrder>4</sortOrder>
			<boxActivation>0</boxActivation>
		</portalboxitem>
		
		<portalboxitem name="rgalleryright">
			<className>RGalleryBox</className>
			<cacheBuilderClass></cacheBuilderClass>
			<boxType>3</boxType>
			<useCache>0</useCache>
			<sortOrder>4</sortOrder>
			<boxActivation>0</boxActivation>
		</portalboxitem>
	</import>
</data>